fars_tts/__init__.py
fars_tts-0.2.dist-info/METADATA
fars_tts-0.2.dist-info/WHEEL
fars_tts-0.2.dist-info/top_level.txt
fars_tts-0.2.dist-info/RECORD
