Metadata-Version: 2.4
Name: fars_tts
Version: 0.2
Summary: Use pertian tts so easy.
Author-email: Amirali <Amir.z.nine.three@gmail.com>
License: MIT
Classifier: Programming Language :: Python :: 3
Classifier: License :: OSI Approved :: MIT License
Classifier: Operating System :: OS Independent
Requires-Python: >=3.10
